<annotation>
	<folder>640 x 480 50_</folder>
	<filename>1103.jpg</filename>
	<path>C:\Users\Solomon Suasb\Desktop\640 x 480 50_\1103.jpg</path>
	<source>
		<database>Unknown</database>
	</source>
	<size>
		<width>640</width>
		<height>480</height>
		<depth>3</depth>
	</size>
	<segmented>0</segmented>
	<object>
		<name>WBC</name>
		<pose>Unspecified</pose>
		<truncated>0</truncated>
		<difficult>0</difficult>
		<bndbox>
			<xmin>384</xmin>
			<ymin>70</ymin>
			<xmax>505</xmax>
			<ymax>189</ymax>
		</bndbox>
	</object>
	<object>
		<name>WBC</name>
		<pose>Unspecified</pose>
		<truncated>0</truncated>
		<difficult>0</difficult>
		<bndbox>
			<xmin>44</xmin>
			<ymin>215</ymin>
			<xmax>137</xmax>
			<ymax>319</ymax>
		</bndbox>
	</object>
	<object>
		<name>RBC</name>
		<pose>Unspecified</pose>
		<truncated>0</truncated>
		<difficult>0</difficult>
		<bndbox>
			<xmin>17</xmin>
			<ymin>36</ymin>
			<xmax>76</xmax>
			<ymax>96</ymax>
		</bndbox>
	</object>
	<object>
		<name>RBC</name>
		<pose>Unspecified</pose>
		<truncated>0</truncated>
		<difficult>0</difficult>
		<bndbox>
			<xmin>19</xmin>
			<ymin>72</ymin>
			<xmax>78</xmax>
			<ymax>132</ymax>
		</bndbox>
	</object>
	<object>
		<name>RBC</name>
		<pose>Unspecified</pose>
		<truncated>1</truncated>
		<difficult>0</difficult>
		<bndbox>
			<xmin>1</xmin>
			<ymin>96</ymin>
			<xmax>59</xmax>
			<ymax>156</ymax>
		</bndbox>
	</object>
	<object>
		<name>RBC</name>
		<pose>Unspecified</pose>
		<truncated>0</truncated>
		<difficult>0</difficult>
		<bndbox>
			<xmin>65</xmin>
			<ymin>96</ymin>
			<xmax>124</xmax>
			<ymax>156</ymax>
		</bndbox>
	</object>
	<object>
		<name>RBC</name>
		<pose>Unspecified</pose>
		<truncated>0</truncated>
		<difficult>0</difficult>
		<bndbox>
			<xmin>108</xmin>
			<ymin>93</ymin>
			<xmax>167</xmax>
			<ymax>153</ymax>
		</bndbox>
	</object>
	<object>
		<name>RBC</name>
		<pose>Unspecified</pose>
		<truncated>0</truncated>
		<difficult>0</difficult>
		<bndbox>
			<xmin>151</xmin>
			<ymin>111</ymin>
			<xmax>210</xmax>
			<ymax>171</ymax>
		</bndbox>
	</object>
	<object>
		<name>RBC</name>
		<pose>Unspecified</pose>
		<truncated>0</truncated>
		<difficult>0</difficult>
		<bndbox>
			<xmin>105</xmin>
			<ymin>145</ymin>
			<xmax>164</xmax>
			<ymax>205</ymax>
		</bndbox>
	</object>
	<object>
		<name>RBC</name>
		<pose>Unspecified</pose>
		<truncated>0</truncated>
		<difficult>0</difficult>
		<bndbox>
			<xmin>70</xmin>
			<ymin>155</ymin>
			<xmax>129</xmax>
			<ymax>215</ymax>
		</bndbox>
	</object>
	<object>
		<name>RBC</name>
		<pose>Unspecified</pose>
		<truncated>0</truncated>
		<difficult>0</difficult>
		<bndbox>
			<xmin>43</xmin>
			<ymin>311</ymin>
			<xmax>102</xmax>
			<ymax>371</ymax>
		</bndbox>
	</object>
	<object>
		<name>RBC</name>
		<pose>Unspecified</pose>
		<truncated>0</truncated>
		<difficult>0</difficult>
		<bndbox>
			<xmin>4</xmin>
			<ymin>297</ymin>
			<xmax>63</xmax>
			<ymax>357</ymax>
		</bndbox>
	</object>
	<object>
		<name>RBC</name>
		<pose>Unspecified</pose>
		<truncated>1</truncated>
		<difficult>0</difficult>
		<bndbox>
			<xmin>1</xmin>
			<ymin>257</ymin>
			<xmax>59</xmax>
			<ymax>317</ymax>
		</bndbox>
	</object>
	<object>
		<name>RBC</name>
		<pose>Unspecified</pose>
		<truncated>0</truncated>
		<difficult>0</difficult>
		<bndbox>
			<xmin>21</xmin>
			<ymin>354</ymin>
			<xmax>80</xmax>
			<ymax>414</ymax>
		</bndbox>
	</object>
	<object>
		<name>RBC</name>
		<pose>Unspecified</pose>
		<truncated>0</truncated>
		<difficult>0</difficult>
		<bndbox>
			<xmin>56</xmin>
			<ymin>355</ymin>
			<xmax>115</xmax>
			<ymax>415</ymax>
		</bndbox>
	</object>
	<object>
		<name>RBC</name>
		<pose>Unspecified</pose>
		<truncated>0</truncated>
		<difficult>0</difficult>
		<bndbox>
			<xmin>46</xmin>
			<ymin>405</ymin>
			<xmax>105</xmax>
			<ymax>465</ymax>
		</bndbox>
	</object>
	<object>
		<name>RBC</name>
		<pose>Unspecified</pose>
		<truncated>1</truncated>
		<difficult>0</difficult>
		<bndbox>
			<xmin>20</xmin>
			<ymin>419</ymin>
			<xmax>79</xmax>
			<ymax>480</ymax>
		</bndbox>
	</object>
	<object>
		<name>RBC</name>
		<pose>Unspecified</pose>
		<truncated>1</truncated>
		<difficult>0</difficult>
		<bndbox>
			<xmin>98</xmin>
			<ymin>419</ymin>
			<xmax>157</xmax>
			<ymax>480</ymax>
		</bndbox>
	</object>
	<object>
		<name>RBC</name>
		<pose>Unspecified</pose>
		<truncated>0</truncated>
		<difficult>0</difficult>
		<bndbox>
			<xmin>206</xmin>
			<ymin>344</ymin>
			<xmax>265</xmax>
			<ymax>404</ymax>
		</bndbox>
	</object>
	<object>
		<name>RBC</name>
		<pose>Unspecified</pose>
		<truncated>0</truncated>
		<difficult>0</difficult>
		<bndbox>
			<xmin>206</xmin>
			<ymin>288</ymin>
			<xmax>265</xmax>
			<ymax>348</ymax>
		</bndbox>
	</object>
	<object>
		<name>RBC</name>
		<pose>Unspecified</pose>
		<truncated>0</truncated>
		<difficult>0</difficult>
		<bndbox>
			<xmin>159</xmin>
			<ymin>242</ymin>
			<xmax>218</xmax>
			<ymax>302</ymax>
		</bndbox>
	</object>
	<object>
		<name>RBC</name>
		<pose>Unspecified</pose>
		<truncated>0</truncated>
		<difficult>0</difficult>
		<bndbox>
			<xmin>177</xmin>
			<ymin>220</ymin>
			<xmax>236</xmax>
			<ymax>280</ymax>
		</bndbox>
	</object>
	<object>
		<name>RBC</name>
		<pose>Unspecified</pose>
		<truncated>0</truncated>
		<difficult>0</difficult>
		<bndbox>
			<xmin>209</xmin>
			<ymin>187</ymin>
			<xmax>268</xmax>
			<ymax>247</ymax>
		</bndbox>
	</object>
	<object>
		<name>RBC</name>
		<pose>Unspecified</pose>
		<truncated>0</truncated>
		<difficult>0</difficult>
		<bndbox>
			<xmin>211</xmin>
			<ymin>173</ymin>
			<xmax>270</xmax>
			<ymax>233</ymax>
		</bndbox>
	</object>
	<object>
		<name>RBC</name>
		<pose>Unspecified</pose>
		<truncated>0</truncated>
		<difficult>0</difficult>
		<bndbox>
			<xmin>177</xmin>
			<ymin>148</ymin>
			<xmax>236</xmax>
			<ymax>208</ymax>
		</bndbox>
	</object>
	<object>
		<name>RBC</name>
		<pose>Unspecified</pose>
		<truncated>0</truncated>
		<difficult>0</difficult>
		<bndbox>
			<xmin>213</xmin>
			<ymin>96</ymin>
			<xmax>272</xmax>
			<ymax>156</ymax>
		</bndbox>
	</object>
	<object>
		<name>RBC</name>
		<pose>Unspecified</pose>
		<truncated>0</truncated>
		<difficult>0</difficult>
		<bndbox>
			<xmin>204</xmin>
			<ymin>49</ymin>
			<xmax>263</xmax>
			<ymax>109</ymax>
		</bndbox>
	</object>
	<object>
		<name>RBC</name>
		<pose>Unspecified</pose>
		<truncated>0</truncated>
		<difficult>0</difficult>
		<bndbox>
			<xmin>253</xmin>
			<ymin>29</ymin>
			<xmax>312</xmax>
			<ymax>89</ymax>
		</bndbox>
	</object>
	<object>
		<name>RBC</name>
		<pose>Unspecified</pose>
		<truncated>0</truncated>
		<difficult>0</difficult>
		<bndbox>
			<xmin>270</xmin>
			<ymin>60</ymin>
			<xmax>329</xmax>
			<ymax>120</ymax>
		</bndbox>
	</object>
	<object>
		<name>RBC</name>
		<pose>Unspecified</pose>
		<truncated>0</truncated>
		<difficult>0</difficult>
		<bndbox>
			<xmin>276</xmin>
			<ymin>120</ymin>
			<xmax>335</xmax>
			<ymax>180</ymax>
		</bndbox>
	</object>
	<object>
		<name>RBC</name>
		<pose>Unspecified</pose>
		<truncated>0</truncated>
		<difficult>0</difficult>
		<bndbox>
			<xmin>323</xmin>
			<ymin>156</ymin>
			<xmax>382</xmax>
			<ymax>216</ymax>
		</bndbox>
	</object>
	<object>
		<name>RBC</name>
		<pose>Unspecified</pose>
		<truncated>0</truncated>
		<difficult>0</difficult>
		<bndbox>
			<xmin>276</xmin>
			<ymin>179</ymin>
			<xmax>335</xmax>
			<ymax>239</ymax>
		</bndbox>
	</object>
	<object>
		<name>RBC</name>
		<pose>Unspecified</pose>
		<truncated>0</truncated>
		<difficult>0</difficult>
		<bndbox>
			<xmin>249</xmin>
			<ymin>231</ymin>
			<xmax>308</xmax>
			<ymax>291</ymax>
		</bndbox>
	</object>
	<object>
		<name>RBC</name>
		<pose>Unspecified</pose>
		<truncated>0</truncated>
		<difficult>0</difficult>
		<bndbox>
			<xmin>309</xmin>
			<ymin>220</ymin>
			<xmax>368</xmax>
			<ymax>280</ymax>
		</bndbox>
	</object>
	<object>
		<name>RBC</name>
		<pose>Unspecified</pose>
		<truncated>0</truncated>
		<difficult>0</difficult>
		<bndbox>
			<xmin>364</xmin>
			<ymin>219</ymin>
			<xmax>423</xmax>
			<ymax>279</ymax>
		</bndbox>
	</object>
	<object>
		<name>RBC</name>
		<pose>Unspecified</pose>
		<truncated>0</truncated>
		<difficult>0</difficult>
		<bndbox>
			<xmin>291</xmin>
			<ymin>276</ymin>
			<xmax>350</xmax>
			<ymax>336</ymax>
		</bndbox>
	</object>
	<object>
		<name>RBC</name>
		<pose>Unspecified</pose>
		<truncated>0</truncated>
		<difficult>0</difficult>
		<bndbox>
			<xmin>270</xmin>
			<ymin>312</ymin>
			<xmax>329</xmax>
			<ymax>372</ymax>
		</bndbox>
	</object>
	<object>
		<name>RBC</name>
		<pose>Unspecified</pose>
		<truncated>0</truncated>
		<difficult>0</difficult>
		<bndbox>
			<xmin>261</xmin>
			<ymin>374</ymin>
			<xmax>320</xmax>
			<ymax>434</ymax>
		</bndbox>
	</object>
	<object>
		<name>RBC</name>
		<pose>Unspecified</pose>
		<truncated>1</truncated>
		<difficult>0</difficult>
		<bndbox>
			<xmin>278</xmin>
			<ymin>419</ymin>
			<xmax>337</xmax>
			<ymax>480</ymax>
		</bndbox>
	</object>
	<object>
		<name>RBC</name>
		<pose>Unspecified</pose>
		<truncated>1</truncated>
		<difficult>0</difficult>
		<bndbox>
			<xmin>327</xmin>
			<ymin>419</ymin>
			<xmax>386</xmax>
			<ymax>480</ymax>
		</bndbox>
	</object>
	<object>
		<name>RBC</name>
		<pose>Unspecified</pose>
		<truncated>0</truncated>
		<difficult>0</difficult>
		<bndbox>
			<xmin>360</xmin>
			<ymin>344</ymin>
			<xmax>419</xmax>
			<ymax>404</ymax>
		</bndbox>
	</object>
	<object>
		<name>RBC</name>
		<pose>Unspecified</pose>
		<truncated>0</truncated>
		<difficult>0</difficult>
		<bndbox>
			<xmin>387</xmin>
			<ymin>354</ymin>
			<xmax>446</xmax>
			<ymax>414</ymax>
		</bndbox>
	</object>
	<object>
		<name>RBC</name>
		<pose>Unspecified</pose>
		<truncated>0</truncated>
		<difficult>0</difficult>
		<bndbox>
			<xmin>358</xmin>
			<ymin>298</ymin>
			<xmax>417</xmax>
			<ymax>358</ymax>
		</bndbox>
	</object>
	<object>
		<name>RBC</name>
		<pose>Unspecified</pose>
		<truncated>0</truncated>
		<difficult>0</difficult>
		<bndbox>
			<xmin>343</xmin>
			<ymin>274</ymin>
			<xmax>402</xmax>
			<ymax>334</ymax>
		</bndbox>
	</object>
	<object>
		<name>RBC</name>
		<pose>Unspecified</pose>
		<truncated>0</truncated>
		<difficult>0</difficult>
		<bndbox>
			<xmin>403</xmin>
			<ymin>250</ymin>
			<xmax>462</xmax>
			<ymax>310</ymax>
		</bndbox>
	</object>
	<object>
		<name>RBC</name>
		<pose>Unspecified</pose>
		<truncated>0</truncated>
		<difficult>0</difficult>
		<bndbox>
			<xmin>415</xmin>
			<ymin>216</ymin>
			<xmax>474</xmax>
			<ymax>276</ymax>
		</bndbox>
	</object>
	<object>
		<name>RBC</name>
		<pose>Unspecified</pose>
		<truncated>0</truncated>
		<difficult>0</difficult>
		<bndbox>
			<xmin>409</xmin>
			<ymin>190</ymin>
			<xmax>468</xmax>
			<ymax>250</ymax>
		</bndbox>
	</object>
	<object>
		<name>RBC</name>
		<pose>Unspecified</pose>
		<truncated>0</truncated>
		<difficult>0</difficult>
		<bndbox>
			<xmin>476</xmin>
			<ymin>168</ymin>
			<xmax>535</xmax>
			<ymax>228</ymax>
		</bndbox>
	</object>
	<object>
		<name>RBC</name>
		<pose>Unspecified</pose>
		<truncated>0</truncated>
		<difficult>0</difficult>
		<bndbox>
			<xmin>513</xmin>
			<ymin>162</ymin>
			<xmax>572</xmax>
			<ymax>222</ymax>
		</bndbox>
	</object>
	<object>
		<name>RBC</name>
		<pose>Unspecified</pose>
		<truncated>0</truncated>
		<difficult>0</difficult>
		<bndbox>
			<xmin>529</xmin>
			<ymin>130</ymin>
			<xmax>588</xmax>
			<ymax>190</ymax>
		</bndbox>
	</object>
	<object>
		<name>RBC</name>
		<pose>Unspecified</pose>
		<truncated>0</truncated>
		<difficult>0</difficult>
		<bndbox>
			<xmin>554</xmin>
			<ymin>56</ymin>
			<xmax>613</xmax>
			<ymax>116</ymax>
		</bndbox>
	</object>
	<object>
		<name>RBC</name>
		<pose>Unspecified</pose>
		<truncated>0</truncated>
		<difficult>0</difficult>
		<bndbox>
			<xmin>519</xmin>
			<ymin>23</ymin>
			<xmax>578</xmax>
			<ymax>83</ymax>
		</bndbox>
	</object>
	<object>
		<name>RBC</name>
		<pose>Unspecified</pose>
		<truncated>0</truncated>
		<difficult>0</difficult>
		<bndbox>
			<xmin>467</xmin>
			<ymin>25</ymin>
			<xmax>526</xmax>
			<ymax>85</ymax>
		</bndbox>
	</object>
	<object>
		<name>RBC</name>
		<pose>Unspecified</pose>
		<truncated>0</truncated>
		<difficult>0</difficult>
		<bndbox>
			<xmin>420</xmin>
			<ymin>4</ymin>
			<xmax>479</xmax>
			<ymax>64</ymax>
		</bndbox>
	</object>
	<object>
		<name>RBC</name>
		<pose>Unspecified</pose>
		<truncated>0</truncated>
		<difficult>0</difficult>
		<bndbox>
			<xmin>394</xmin>
			<ymin>21</ymin>
			<xmax>453</xmax>
			<ymax>81</ymax>
		</bndbox>
	</object>
	<object>
		<name>RBC</name>
		<pose>Unspecified</pose>
		<truncated>0</truncated>
		<difficult>0</difficult>
		<bndbox>
			<xmin>348</xmin>
			<ymin>27</ymin>
			<xmax>407</xmax>
			<ymax>87</ymax>
		</bndbox>
	</object>
	<object>
		<name>RBC</name>
		<pose>Unspecified</pose>
		<truncated>0</truncated>
		<difficult>0</difficult>
		<bndbox>
			<xmin>321</xmin>
			<ymin>63</ymin>
			<xmax>380</xmax>
			<ymax>123</ymax>
		</bndbox>
	</object>
	<object>
		<name>RBC</name>
		<pose>Unspecified</pose>
		<truncated>0</truncated>
		<difficult>0</difficult>
		<bndbox>
			<xmin>302</xmin>
			<ymin>14</ymin>
			<xmax>361</xmax>
			<ymax>74</ymax>
		</bndbox>
	</object>
	<object>
		<name>RBC</name>
		<pose>Unspecified</pose>
		<truncated>1</truncated>
		<difficult>0</difficult>
		<bndbox>
			<xmin>581</xmin>
			<ymin>180</ymin>
			<xmax>640</xmax>
			<ymax>240</ymax>
		</bndbox>
	</object>
	<object>
		<name>RBC</name>
		<pose>Unspecified</pose>
		<truncated>0</truncated>
		<difficult>0</difficult>
		<bndbox>
			<xmin>566</xmin>
			<ymin>233</ymin>
			<xmax>625</xmax>
			<ymax>293</ymax>
		</bndbox>
	</object>
	<object>
		<name>RBC</name>
		<pose>Unspecified</pose>
		<truncated>0</truncated>
		<difficult>0</difficult>
		<bndbox>
			<xmin>540</xmin>
			<ymin>232</ymin>
			<xmax>599</xmax>
			<ymax>292</ymax>
		</bndbox>
	</object>
	<object>
		<name>RBC</name>
		<pose>Unspecified</pose>
		<truncated>0</truncated>
		<difficult>0</difficult>
		<bndbox>
			<xmin>479</xmin>
			<ymin>277</ymin>
			<xmax>538</xmax>
			<ymax>337</ymax>
		</bndbox>
	</object>
	<object>
		<name>RBC</name>
		<pose>Unspecified</pose>
		<truncated>0</truncated>
		<difficult>0</difficult>
		<bndbox>
			<xmin>454</xmin>
			<ymin>290</ymin>
			<xmax>513</xmax>
			<ymax>350</ymax>
		</bndbox>
	</object>
	<object>
		<name>RBC</name>
		<pose>Unspecified</pose>
		<truncated>0</truncated>
		<difficult>0</difficult>
		<bndbox>
			<xmin>467</xmin>
			<ymin>346</ymin>
			<xmax>526</xmax>
			<ymax>406</ymax>
		</bndbox>
	</object>
	<object>
		<name>RBC</name>
		<pose>Unspecified</pose>
		<truncated>0</truncated>
		<difficult>0</difficult>
		<bndbox>
			<xmin>510</xmin>
			<ymin>317</ymin>
			<xmax>569</xmax>
			<ymax>377</ymax>
		</bndbox>
	</object>
	<object>
		<name>RBC</name>
		<pose>Unspecified</pose>
		<truncated>0</truncated>
		<difficult>0</difficult>
		<bndbox>
			<xmin>549</xmin>
			<ymin>304</ymin>
			<xmax>608</xmax>
			<ymax>364</ymax>
		</bndbox>
	</object>
	<object>
		<name>RBC</name>
		<pose>Unspecified</pose>
		<truncated>1</truncated>
		<difficult>0</difficult>
		<bndbox>
			<xmin>581</xmin>
			<ymin>277</ymin>
			<xmax>640</xmax>
			<ymax>337</ymax>
		</bndbox>
	</object>
	<object>
		<name>RBC</name>
		<pose>Unspecified</pose>
		<truncated>0</truncated>
		<difficult>0</difficult>
		<bndbox>
			<xmin>550</xmin>
			<ymin>371</ymin>
			<xmax>609</xmax>
			<ymax>431</ymax>
		</bndbox>
	</object>
	<object>
		<name>RBC</name>
		<pose>Unspecified</pose>
		<truncated>1</truncated>
		<difficult>0</difficult>
		<bndbox>
			<xmin>458</xmin>
			<ymin>419</ymin>
			<xmax>517</xmax>
			<ymax>480</ymax>
		</bndbox>
	</object>
	<object>
		<name>RBC</name>
		<pose>Unspecified</pose>
		<truncated>0</truncated>
		<difficult>0</difficult>
		<bndbox>
			<xmin>466</xmin>
			<ymin>385</ymin>
			<xmax>525</xmax>
			<ymax>445</ymax>
		</bndbox>
	</object>
	<object>
		<name>RBC</name>
		<pose>Unspecified</pose>
		<truncated>0</truncated>
		<difficult>0</difficult>
		<bndbox>
			<xmin>146</xmin>
			<ymin>50</ymin>
			<xmax>205</xmax>
			<ymax>110</ymax>
		</bndbox>
	</object>
	<object>
		<name>RBC</name>
		<pose>Unspecified</pose>
		<truncated>0</truncated>
		<difficult>0</difficult>
		<bndbox>
			<xmin>180</xmin>
			<ymin>48</ymin>
			<xmax>239</xmax>
			<ymax>108</ymax>
		</bndbox>
	</object>
	<object>
		<name>RBC</name>
		<pose>Unspecified</pose>
		<truncated>0</truncated>
		<difficult>0</difficult>
		<bndbox>
			<xmin>82</xmin>
			<ymin>6</ymin>
			<xmax>141</xmax>
			<ymax>66</ymax>
		</bndbox>
	</object>
	<object>
		<name>RBC</name>
		<pose>Unspecified</pose>
		<truncated>1</truncated>
		<difficult>0</difficult>
		<bndbox>
			<xmin>137</xmin>
			<ymin>1</ymin>
			<xmax>196</xmax>
			<ymax>60</ymax>
		</bndbox>
	</object>
	<object>
		<name>RBC</name>
		<pose>Unspecified</pose>
		<truncated>1</truncated>
		<difficult>0</difficult>
		<bndbox>
			<xmin>207</xmin>
			<ymin>1</ymin>
			<xmax>266</xmax>
			<ymax>60</ymax>
		</bndbox>
	</object>
</annotation>
